crczp/cloud_commons/__init__.py
crczp/cloud_commons/cloud_client_base.py
crczp/cloud_commons/cloud_client_elements.py
crczp/cloud_commons/exceptions.py
crczp/cloud_commons/topology_elements.py
crczp/cloud_commons/topology_instance.py
crczp/cloud_commons/transformation_configuration.py
crczp_python_commons-1.0.2.dist-info/METADATA
crczp_python_commons-1.0.2.dist-info/WHEEL
crczp_python_commons-1.0.2.dist-info/licenses/LICENSE
crczp_python_commons-1.0.2.dist-info/RECORD
