Metadata-Version: 2.4
Name: crczp-python-commons
Version: 1.0.2
Summary: crczp python commons
Author: cybersecurityhub.cz
License-Expression: MIT
License-File: LICENSE
Requires-Python: >=3.9
Requires-Dist: crczp-topology-definition>=1.0.0
